decoyfree_msfdr/__init__.py
decoyfree_msfdr/constraints.py
decoyfree_msfdr/fixed_normal.py
decoyfree_msfdr/gpu.py
decoyfree_msfdr/mixture_model_base.py
decoyfree_msfdr/model.json
decoyfree_msfdr/ms_launcher.py
decoyfree_msfdr/ms_mixture_model.py
decoyfree_msfdr/ms_mixture_model_1S.py
decoyfree_msfdr/ms_mixture_model_base.py
decoyfree_msfdr/myutils.py
decoyfree_msfdr/normal.py
decoyfree_msfdr/normal_gpu.py
decoyfree_msfdr/param_binary_search.py
decoyfree_msfdr/skew_normal.py
decoyfree_msfdr/xlms_launcher.py
decoyfree_msfdr/xlms_mixture_model.py
decoyfree_msfdr/xlms_mixture_model_1S.py
decoyfree_msfdr/kanren/__init__.py
decoyfree_msfdr/kanren/arith.py
decoyfree_msfdr/kanren/assoccomm.py
decoyfree_msfdr/kanren/cons.py
decoyfree_msfdr/kanren/core.py
decoyfree_msfdr/kanren/dispatch.py
decoyfree_msfdr/kanren/facts.py
decoyfree_msfdr/kanren/goals.py
decoyfree_msfdr/kanren/term.py
decoyfree_msfdr/kanren/util.py
decoyfree_msfdr/msparser/__init__.py
decoyfree_msfdr/msparser/csv.py
decoyfree_msfdr/msparser/extract_search_result.py
decoyfree_msfdr/msparser/idxml.py
decoyfree_msfdr/msparser/load_search_result.py
decoyfree_msfdr/msparser/ms.py
decoyfree_msfdr/msparser/tsv.py
decoyfree_msfdr/msparser/xlms.py
decoyfree_msfdr-0.1.3.dist-info/METADATA
decoyfree_msfdr-0.1.3.dist-info/WHEEL
decoyfree_msfdr-0.1.3.dist-info/entry_points.txt
decoyfree_msfdr-0.1.3.dist-info/licenses/LICENSE
decoyfree_msfdr-0.1.3.dist-info/RECORD
