Metadata-Version: 2.3
Name: DecoyFree-MSFDR
Version: 0.1.3
Summary: A package to estimate FDR in mass-spectrometry searching results using decoy-free approach
Project-URL: Homepage, https://github.com/shawn-peng/DecoyFree-MSFDR
Project-URL: Bug Tracker, https://github.com/shawn-peng/DecoyFree-MSFDR/issues
Author-email: Yisu Peng <yisupeng@gmail.com>
License-File: LICENSE
Classifier: License :: OSI Approved :: MIT License
Classifier: Operating System :: OS Independent
Classifier: Programming Language :: Python :: 3
Requires-Python: >=3.7
Requires-Dist: hdf5storage
Requires-Dist: logical-unification
Requires-Dist: matplotlib
Requires-Dist: pandas
Requires-Dist: pymzml
Requires-Dist: scipy
Requires-Dist: sympy
Requires-Dist: torchquad
